LICENSE
MANIFEST.in
README.rst
setup.py
bin/pantograph
biopantograph/BiGG.py
biopantograph/BiGG2SBML.py
biopantograph/SBMLeditor.py
biopantograph/SBMLutils.py
biopantograph/__init__.py
biopantograph/logic.py
biopantograph/pathtastictools.py
biopantograph/ptg_addbiggreactions.py
biopantograph/ptg_curateSBML.py
biopantograph/ptg_inparanoid2rel.py
biopantograph/ptg_omcl2rel.py
biopantograph/ptg_projector.py
biopantograph.egg-info/PKG-INFO
biopantograph.egg-info/SOURCES.txt
biopantograph.egg-info/dependency_links.txt
biopantograph.egg-info/entry_points.txt
biopantograph.egg-info/requires.txt
biopantograph.egg-info/top_level.txt