Metadata-Version: 1.1
Name: biopantograph
Version: 0.3.2
Summary: Pantograph is a toolbox for the reconstruction, curation and validation of metabolic models.
Home-page: http://pathtastic.gforge.inria.fr
Author: Nicolas Loira
Author-email: nloira@gmail.com
License: GPLv2
Keywords: pantograph metabolic model reconstruction
Platform: UNKNOWN
Classifier: Development Status :: 3 - Alpha
Classifier: Environment :: Console
Classifier: Intended Audience :: Science/Research
Classifier: License :: OSI Approved :: GNU General Public License v2 (GPLv2)
Classifier: Programming Language :: Python :: 2.7
Classifier: Topic :: Scientific/Engineering :: Bio-Informatics
